iblm/__init__.py
iblm/exceptions.py
iblm/ibl.py
iblm/iblbagging/__init__.py
iblm/iblbagging/iblbagging.py
iblm/prompt_templates/__init__.py
iblm/prompt_templates/claude-3-opus-20240229/ibl/__init__.py
iblm/prompt_templates/claude-3-opus-20240229/ibl/binary.j2
iblm/prompt_templates/claude-3-opus-20240229/ibl/interpret.j2
iblm/prompt_templates/claude-3-opus-20240229/ibl/regression.j2
iblm/prompt_templates/claude-3-sonnet-20240229/ibl/__init__.py
iblm/prompt_templates/claude-3-sonnet-20240229/ibl/binary.j2
iblm/prompt_templates/claude-3-sonnet-20240229/ibl/interpret.j2
iblm/prompt_templates/gemini-pro/ibl/__init__.py
iblm/prompt_templates/gemini-pro/ibl/binary.j2
iblm/prompt_templates/gemini-pro/ibl/interpret.j2
iblm/prompt_templates/gemini-pro/ibl/regression.j2
iblm/prompt_templates/gpt-35-turbo-0125/ibl/__init__.py
iblm/prompt_templates/gpt-35-turbo-0125/ibl/binary.j2
iblm/prompt_templates/gpt-35-turbo-0125/ibl/interpret.j2
iblm/prompt_templates/gpt-4-0125-preview/__init__.py
iblm/prompt_templates/gpt-4-0125-preview/ibl/__init__.py
iblm/prompt_templates/gpt-4-0125-preview/ibl/binary.j2
iblm/prompt_templates/gpt-4-0125-preview/ibl/interpret.j2
iblm/prompt_templates/gpt-4-0125-preview/ibl/regression.j2
iblm/prompt_templates/iblboosting/fit.j2
iblm/utils/llm_client.py
iblm/utils/metrics.py
iblm/utils/prompt.py
iblm-1.0.6.dist-info/LICENSE
iblm-1.0.6.dist-info/METADATA
iblm-1.0.6.dist-info/WHEEL
iblm-1.0.6.dist-info/RECORD
