Metadata-Version: 2.1
Name: iblm
Version: 1.0.6
Summary: Inductive-bias Learning
License: MIT
Author: toma tanaka
Author-email: ulti4929@gmail.com
Requires-Python: >=3.9,<3.12
Classifier: License :: OSI Approved :: MIT License
Classifier: Programming Language :: Python :: 3
Classifier: Programming Language :: Python :: 3.9
Classifier: Programming Language :: Python :: 3.10
Classifier: Programming Language :: Python :: 3.11
Requires-Dist: anthropic (>=0.19.1,<0.20.0)
Requires-Dist: datasets (>=2.13.1,<3.0.0)
Requires-Dist: google-generativeai (>=0.3.2,<0.4.0)
Requires-Dist: jinja2 (>=3.1.0,<4.0.0)
Requires-Dist: numpy (>=1.21,<1.24)
Requires-Dist: openai (==1.3.7)
Requires-Dist: pandas (==1.4.0)
Requires-Dist: scikit-learn (>=1.2.2,<2.0.0)
Requires-Dist: tqdm (>=4.65.0,<5.0.0)
